{
  "title": "Notre Histoire",
  "subtitle": "Une histoire de passion maritime, d'expertise en œufs de mulet et d'engagement environnemental",
  "hero_image": "/images/a1f6e6093a336fbe1c61ed2c8b68173c.jpg",
  "story_title": "Notre Histoire",
  "story_content": "Fondée il y a plus de 10 ans, HEMAM & FILS est née de la passion d'une famille mauritanienne pour la mer et ses ressources. Notre entreprise s'est développée en alliant les méthodes traditionnelles de la pêche artisanale aux exigences du commerce international.\n\nSpécialiste de l'exportation d'œufs de mulet destinés à la fabrication de la poutargue, HEMAM & FILS s'impose comme un acteur de référence dans le secteur des produits de la mer haut de gamme.\n\nDepuis 2003, nous détenons une licence CEE renouvelée annuellement, témoignage de notre engagement envers l'excellence, la traçabilité et le respect des standards d'exportation.",
  "story_image": "https://i.postimg.cc/vZvQBK5T/IMG-7222.jpg"
}